automation_ide/__init__.py
automation_ide/__main__.py
automation_ide/automation_editor_ui/__init__.py
automation_ide/automation_editor_ui/connect_gui/__init__.py
automation_ide/automation_editor_ui/connect_gui/ssh/__init__.py
automation_ide/automation_editor_ui/connect_gui/ssh/ssh_command_widget.py
automation_ide/automation_editor_ui/connect_gui/ssh/ssh_file_viewer_widget.py
automation_ide/automation_editor_ui/connect_gui/ssh/ssh_login_widget.py
automation_ide/automation_editor_ui/connect_gui/ssh/ssh_main_widget.py
automation_ide/automation_editor_ui/connect_gui/url/__init__.py
automation_ide/automation_editor_ui/connect_gui/url/ai_code_review_gui.py
automation_ide/automation_editor_ui/editor_main/__init__.py
automation_ide/automation_editor_ui/editor_main/main_ui.py
automation_ide/automation_editor_ui/extend_ai_gui/__init__.py
automation_ide/automation_editor_ui/extend_ai_gui/ai_gui_global_variable.py
automation_ide/automation_editor_ui/extend_ai_gui/cot_code_review_gui.py
automation_ide/automation_editor_ui/extend_ai_gui/prompt_edit_gui/__init__.py
automation_ide/automation_editor_ui/extend_ai_gui/prompt_edit_gui/cot_prompt_editor_widget.py
automation_ide/automation_editor_ui/extend_ai_gui/prompt_edit_gui/skills_prompt_editor_widget.py
automation_ide/automation_editor_ui/extend_ai_gui/prompt_edit_gui/cot_code_review_prompt_templates/__init__.py
automation_ide/automation_editor_ui/extend_ai_gui/prompt_edit_gui/cot_code_review_prompt_templates/code_smell_detector.py
automation_ide/automation_editor_ui/extend_ai_gui/prompt_edit_gui/cot_code_review_prompt_templates/first_code_review.py
automation_ide/automation_editor_ui/extend_ai_gui/prompt_edit_gui/cot_code_review_prompt_templates/first_summary_prompt.py
automation_ide/automation_editor_ui/extend_ai_gui/prompt_edit_gui/cot_code_review_prompt_templates/global_rule.py
automation_ide/automation_editor_ui/extend_ai_gui/prompt_edit_gui/cot_code_review_prompt_templates/judge.py
automation_ide_dev-0.0.70.dist-info/licenses/LICENSE
automation_ide_dev-0.0.70.dist-info/METADATA
automation_ide_dev-0.0.70.dist-info/WHEEL
automation_ide_dev-0.0.70.dist-info/top_level.txt
automation_ide_dev-0.0.70.dist-info/RECORD
